cni_tlbx/HGR.py
cni_tlbx/IRM.py
cni_tlbx/PEA.py
cni_tlbx/__init__.py
cni_tlbx/gadgets.py
cni_tlbx/pRF.py
cni_tlbx-1.0.1.dist-info/METADATA
cni_tlbx-1.0.1.dist-info/WHEEL
cni_tlbx-1.0.1.dist-info/top_level.txt
cni_tlbx-1.0.1.dist-info/RECORD
