Metadata-Version: 2.1
Name: cni-tlbx
Version: 1.0.1
Summary: computational neuroimaging toolbox
Home-page: https://github.com/ccnmaastricht/CNI_toolbox
Author: Mario Senden
Author-email: mario.senden@maastrichtuniversity.nl
License: UNKNOWN
Platform: UNKNOWN
Classifier: Programming Language :: Python :: 3
Classifier: License :: OSI Approved :: GNU Lesser General Public License v3 (LGPLv3)
Classifier: Operating System :: OS Independent
Requires-Python: >=3
Requires-Dist: numpy (>=1.18.3)
Requires-Dist: scipy (>=1.4.1)
Requires-Dist: opencv-python (>=4.2.0.34)
